wbiztool_client/__init__.py
wbiztool_client/client.py
wbiztool_client-1.0.2.dist-info/licenses/LICENSE
wbiztool_client-1.0.2.dist-info/METADATA
wbiztool_client-1.0.2.dist-info/WHEEL
wbiztool_client-1.0.2.dist-info/top_level.txt
wbiztool_client-1.0.2.dist-info/RECORD
