Metadata-Version: 2.4
Name: wbiztool-client
Version: 1.0.2
Summary: Python client for the WbizTool WhatsApp messaging API
Home-page: https://github.com/anuragmeena92/wbiztool-client
Author: Anurag Meena
Author-email: anuragmeena92@gmail.com
Project-URL: Documentation, https://wbiztool.com/docs/
Project-URL: Source, https://github.com/anuragmeena92/wbiztool-client
Project-URL: Tracker, https://github.com/anuragmeena92/wbiztool-client/issues
Project-URL: Official Website, https://wbiztool.com
Project-URL: Support, https://wbiztool.com/contact
Keywords: wbiztool,whatsapp,api,client,messaging,communication
Classifier: Development Status :: 4 - Beta
Classifier: Intended Audience :: Developers
Classifier: License :: OSI Approved :: MIT License
Classifier: Programming Language :: Python :: 3
Classifier: Programming Language :: Python :: 3.6
Classifier: Programming Language :: Python :: 3.7
Classifier: Programming Language :: Python :: 3.8
Classifier: Programming Language :: Python :: 3.9
Classifier: Programming Language :: Python :: 3.10
Classifier: Programming Language :: Python :: 3.11
Classifier: Programming Language :: Python :: 3.12
Classifier: Topic :: Communications :: Chat
Classifier: Topic :: Software Development :: Libraries :: Python Modules
Requires-Python: >=3.6
License-File: LICENSE
Requires-Dist: requests>=2.25.0
Dynamic: author
Dynamic: author-email
Dynamic: classifier
Dynamic: description
Dynamic: description-content-type
Dynamic: home-page
Dynamic: keywords
Dynamic: license-file
Dynamic: project-url
Dynamic: requires-dist
Dynamic: requires-python
Dynamic: summary
